{
  "lessons": [
    {
      "id": "d1-cumulative-drills",
      "level": "C1",
      "title": "D1 — Cumulative Drills & Analytics Hooks",
      "slug": "d1-cumulative-drills",
      "tags": [
        "drills",
        "analytics",
        "mixed",
        "c1"
      ],
      "markdown": "# 📊 D1 — Cumulative Drills & Analytics Hooks\\n\\n**Objetivo:** detectar lagunas en contrastes claves y redirigir a la lección de refuerzo adecuada. Cada ejercicio lleva su lessonId de origen para que el panel analítico pueda sugerir la lectura correspondiente.\\n\\n---\\n\\n## Cómo usar este set\\n1. Responde cada item sin mirar apuntes.\\n2. Consulta la retroalimentación y anota los temas que requieren repaso.\\n3. Usa el lessonId vinculado para saltar a la explicación.\\n\\n| Bloque | Qué destapa | Lección de repaso |\\n|---|---|---|\\n| Perfecto vs indefinido | Alcance temporal y marcadores | b1-preterito-perfecto |\\n| Imperfecto vs indefinido | Fondo vs evento | b1-imperfecto-vs-indefinido |\\n| Indicativo vs subjuntivo | Valor epistémico vs modal | a28-subjunctive-sequence |\\n| Clíticos y se | Orden pronominal y duplicaciones | a25-clitics-se |\\n| Por / para | Meta vs causa | a32-por-para-advanced |\\n| Errores francófonos | Falsos amigos y preposiciones | a37-error-bank |\\n\\n> 💡 **Analytics hook:** usa `meta.topic` para filtrar por bloque (`d1:perfecto-vs-indefinido`, etc.) y agrupa respuestas erradas por lessonId para disparar micro-remediaciones.",
      "references": [
        "b1-preterito-perfecto",
        "b1-imperfecto-vs-indefinido",
        "a28-subjunctive-sequence",
        "a25-clitics-se",
        "a32-por-para-advanced",
        "a37-error-bank"
      ]
    }
  ],
  "exercises": [
    {
      "id": "d1-perfecto-indefinido-ex1",
      "lessonId": "b1-preterito-perfecto",
      "type": "cloze",
      "promptMd": "D1 Drill — Esta mañana ___ (terminar, yo) el informe.",
      "answer": "he terminado",
      "accepted": [
        "re:^he terminado$"
      ],
      "feedback": {
        "correct": "Correcto: periodo aún vigente en el día → pretérito perfecto compuesto.",
        "wrong": "Cuando el marco temporal sigue abierto (\"esta mañana\"), usa **he terminado** en variedad peninsular."
      },
      "meta": {
        "difficulty": "B2",
        "skills": [
          "write"
        ],
        "topic": "d1:perfecto-vs-indefinido"
      }
    },
    {
      "id": "d1-perfecto-indefinido-ex2",
      "lessonId": "b1-preterito-perfecto",
      "type": "mcq",
      "promptMd": "D1 Drill — Selecciona la forma natural en España: *¿___ ya la nueva serie?*",
      "options": [
        "Has visto",
        "Viste",
        "Veías"
      ],
      "answer": "Has visto",
      "feedback": {
        "correct": "Correcto: la pregunta sobre experiencia reciente usa pretérito perfecto.",
        "wrong": "Para una experiencia aún conectada al presente, elige **Has visto**."
      },
      "meta": {
        "difficulty": "B1",
        "skills": [
          "read"
        ],
        "topic": "d1:perfecto-vs-indefinido"
      }
    },
    {
      "id": "d1-perfecto-indefinido-ex3",
      "lessonId": "b1-preterito-perfecto",
      "type": "cloze",
      "promptMd": "D1 Drill — Ayer ___ (cerrar, nosotros) la campaña con un acto final.",
      "answer": "cerramos",
      "accepted": [
        "re:^cerramos$"
      ],
      "feedback": {
        "correct": "Correcto: \"ayer\" cierra el marco temporal → indefinido.",
        "wrong": "Los marcadores terminados como *ayer* exigen indefinido: **cerramos**."
      },
      "meta": {
        "difficulty": "B1",
        "skills": [
          "write"
        ],
        "topic": "d1:perfecto-vs-indefinido"
      }
    },
    {
      "id": "d1-perfecto-indefinido-ex4",
      "lessonId": "b1-preterito-perfecto",
      "type": "cloze",
      "promptMd": "D1 Drill — Nunca ___ (probar, yo) la carne de reno.",
      "answer": "he probado",
      "accepted": [
        "re:^he probado$"
      ],
      "feedback": {
        "correct": "Correcto: \"nunca\" señala experiencia vital → pretérito perfecto.",
        "wrong": "Para experiencias sin tiempo concreto usa **he probado** (aunque la respuesta sea negativa)."
      },
      "meta": {
        "difficulty": "B2",
        "skills": [
          "write"
        ],
        "topic": "d1:perfecto-vs-indefinido"
      }
    },
    {
      "id": "d1-perfecto-indefinido-ex5",
      "lessonId": "b1-preterito-perfecto",
      "type": "mcq",
      "promptMd": "D1 Drill — ¿Qué marcador favorece el pretérito perfecto compuesto?",
      "options": [
        "esta semana",
        "ayer",
        "el año pasado"
      ],
      "answer": "esta semana",
      "feedback": {
        "correct": "Correcto: marco vigente → perfecto.",
        "wrong": "Los marcos abiertos como *esta semana* activan **he/has/ha**."
      },
      "meta": {
        "difficulty": "A2",
        "skills": [
          "read"
        ],
        "topic": "d1:perfecto-vs-indefinido"
      }
    },
    {
      "id": "d1-imperfecto-indefinido-ex1",
      "lessonId": "b1-imperfecto-vs-indefinido",
      "type": "cloze",
      "promptMd": "D1 Drill — Cuando ___ (ser, ella) niña, veraneaba en Bretaña.",
      "answer": "era",
      "accepted": [
        "re:^era$"
      ],
      "feedback": {
        "correct": "Correcto: descripción de fondo → imperfecto.",
        "wrong": "Las descripciones de edad y contexto usan **era**."
      },
      "meta": {
        "difficulty": "A2",
        "skills": [
          "write"
        ],
        "topic": "d1:imperfecto-vs-indefinido"
      }
    },
    {
      "id": "d1-imperfecto-indefinido-ex2",
      "lessonId": "b1-imperfecto-vs-indefinido",
      "type": "cloze",
      "promptMd": "D1 Drill — De repente ___ (sonar) el teléfono y nos sobresaltamos.",
      "answer": "sonó",
      "accepted": [
        "re:^sonó$"
      ],
      "feedback": {
        "correct": "Correcto: evento puntual → indefinido.",
        "wrong": "Las irrupciones repentinas van en indefinido: **sonó**."
      },
      "meta": {
        "difficulty": "B1",
        "skills": [
          "write"
        ],
        "topic": "d1:imperfecto-vs-indefinido"
      }
    },
    {
      "id": "d1-imperfecto-indefinido-ex3",
      "lessonId": "b1-imperfecto-vs-indefinido",
      "type": "cloze",
      "promptMd": "D1 Drill — Mientras nosotros ___ (cocinar), ellos llegaron con postre.",
      "answer": "cocinábamos",
      "accepted": [
        "re:^cocinábamos$"
      ],
      "feedback": {
        "correct": "Correcto: acción en progreso paralela → imperfecto.",
        "wrong": "Tras *mientras* usa imperfecto: **cocinábamos**."
      },
      "meta": {
        "difficulty": "B1",
        "skills": [
          "write"
        ],
        "topic": "d1:imperfecto-vs-indefinido"
      }
    },
    {
      "id": "d1-imperfecto-indefinido-ex4",
      "lessonId": "b1-imperfecto-vs-indefinido",
      "type": "mcq",
      "promptMd": "D1 Drill — ___ una tarde fría cuando salió el sol.",
      "options": [
        "Era",
        "Fue",
        "Ha sido"
      ],
      "answer": "Era",
      "feedback": {
        "correct": "Correcto: fondo descriptivo → imperfecto.",
        "wrong": "Para pintar el telón de fondo usa **Era**."
      },
      "meta": {
        "difficulty": "A2",
        "skills": [
          "read"
        ],
        "topic": "d1:imperfecto-vs-indefinido"
      }
    },
    {
      "id": "d1-imperfecto-indefinido-ex5",
      "lessonId": "b1-imperfecto-vs-indefinido",
      "type": "cloze",
      "promptMd": "D1 Drill — A las ocho ___ (empezar) la reunión puntualmente.",
      "answer": "empezó",
      "accepted": [
        "re:^empezó$"
      ],
      "feedback": {
        "correct": "Correcto: acción puntual con hora específica → indefinido.",
        "wrong": "Cuando indicas hora concreta del evento, usa **empezó**."
      },
      "meta": {
        "difficulty": "B1",
        "skills": [
          "write"
        ],
        "topic": "d1:imperfecto-vs-indefinido"
      }
    },
    {
      "id": "d1-indicativo-subjuntivo-ex1",
      "lessonId": "a28-subjunctive-sequence",
      "type": "cloze",
      "promptMd": "D1 Drill — No creo que ___ (ser) buena idea.",
      "answer": "sea",
      "accepted": [
        "re:^sea$"
      ],
      "feedback": {
        "correct": "Correcto: verbo de opinión en negativo → subjuntivo.",
        "wrong": "Tras *no creo que* necesitas subjuntivo: **sea**."
      },
      "meta": {
        "difficulty": "B2",
        "skills": [
          "write"
        ],
        "topic": "d1:indicativo-vs-subjuntivo"
      }
    },
    {
      "id": "d1-indicativo-subjuntivo-ex2",
      "lessonId": "a28-subjunctive-sequence",
      "type": "cloze",
      "promptMd": "D1 Drill — Buscamos a alguien que ___ (hablar) francés con fluidez.",
      "answer": "hable",
      "accepted": [
        "re:^hable$"
      ],
      "feedback": {
        "correct": "Correcto: antecedente indefinido → subjuntivo.",
        "wrong": "Cuando el antecedente es indefinido o hipotético, usa **hable**."
      },
      "meta": {
        "difficulty": "C1",
        "skills": [
          "write"
        ],
        "topic": "d1:indicativo-vs-subjuntivo"
      }
    },
    {
      "id": "d1-indicativo-subjuntivo-ex3",
      "lessonId": "a28-subjunctive-sequence",
      "type": "mcq",
      "promptMd": "D1 Drill — Es evidente que ella ___ experiencia en ventas.",
      "options": [
        "tiene",
        "tenga",
        "tuviera"
      ],
      "answer": "tiene",
      "feedback": {
        "correct": "Correcto: certeza + \"es evidente que\" → indicativo.",
        "wrong": "Las expresiones de certeza mantienen indicativo: **tiene**."
      },
      "meta": {
        "difficulty": "B1",
        "skills": [
          "read"
        ],
        "topic": "d1:indicativo-vs-subjuntivo"
      }
    },
    {
      "id": "d1-indicativo-subjuntivo-ex4",
      "lessonId": "a28-subjunctive-sequence",
      "type": "cloze",
      "promptMd": "D1 Drill — Te llamaré cuando ___ (llegar) a casa.",
      "answer": "llegue",
      "accepted": [
        "re:^llegue$"
      ],
      "feedback": {
        "correct": "Correcto: acción futura pendiente tras *cuando* → subjuntivo.",
        "wrong": "Con acciones futuras tras *cuando*, usa **llegue**."
      },
      "meta": {
        "difficulty": "B2",
        "skills": [
          "write"
        ],
        "topic": "d1:indicativo-vs-subjuntivo"
      }
    },
    {
      "id": "d1-indicativo-subjuntivo-ex5",
      "lessonId": "a28-subjunctive-sequence",
      "type": "mcq",
      "promptMd": "D1 Drill — Aunque ___ caro, lo compraré.",
      "options": [
        "sea",
        "es",
        "fue"
      ],
      "answer": "sea",
      "feedback": {
        "correct": "Correcto: concesión hipotética → subjuntivo.",
        "wrong": "Para una concesión con posibilidad, usa **sea**."
      },
      "meta": {
        "difficulty": "B2",
        "skills": [
          "read"
        ],
        "topic": "d1:indicativo-vs-subjuntivo"
      }
    },
    {
      "id": "d1-cliticos-se-ex1",
      "lessonId": "a25-clitics-se",
      "type": "cloze",
      "promptMd": "D1 Drill — ¿Puedes ___ mañana? (dar + se + lo)",
      "answer": "dárselo",
      "accepted": [
        "re:^dárselo$",
        "re:^darselo$"
      ],
      "feedback": {
        "correct": "Correcto: en infinitivo afirmativo los clíticos se posponen y unen.",
        "wrong": "En infinitivo, coloca los pronombres detrás: **dárselo**."
      },
      "meta": {
        "difficulty": "B2",
        "skills": [
          "write"
        ],
        "topic": "d1:cliticos-se"
      }
    },
    {
      "id": "d1-cliticos-se-ex2",
      "lessonId": "a25-clitics-se",
      "type": "mcq",
      "promptMd": "D1 Drill — Entrega el informe a Marta →",
      "options": [
        "Entrégaselo",
        "Entrégalo",
        "Se lo entrega"
      ],
      "answer": "Entrégaselo",
      "feedback": {
        "correct": "Correcto: imperativo afirmativo + doble pronombre = posposición con tilde.",
        "wrong": "En imperativo afirmativo añade ambos pronombres al final: **Entrégaselo**."
      },
      "meta": {
        "difficulty": "B2",
        "skills": [
          "read"
        ],
        "topic": "d1:cliticos-se"
      }
    },
    {
      "id": "d1-cliticos-se-ex3",
      "lessonId": "a25-clitics-se",
      "type": "cloze",
      "promptMd": "D1 Drill — No ___ dije porque ya lo sabía.",
      "answer": "se lo",
      "accepted": [
        "re:^se lo$"
      ],
      "feedback": {
        "correct": "Correcto: en negativo, los pronombres van delante del verbo conjugado.",
        "wrong": "Con estructuras negativas, coloca los clíticos antes: **no se lo dije**."
      },
      "meta": {
        "difficulty": "A2",
        "skills": [
          "write"
        ],
        "topic": "d1:cliticos-se"
      }
    },
    {
      "id": "d1-cliticos-se-ex4",
      "lessonId": "a25-clitics-se",
      "type": "mcq",
      "promptMd": "D1 Drill — Les di el libro a mis padres →",
      "options": [
        "Se lo di",
        "Les lo di",
        "Lo se di"
      ],
      "answer": "Se lo di",
      "feedback": {
        "correct": "Correcto: \"le/les\" + lo/la se convierte en **se lo**.",
        "wrong": "Con objetos directo e indirecto de tercera persona usa **se lo di**."
      },
      "meta": {
        "difficulty": "B1",
        "skills": [
          "read"
        ],
        "topic": "d1:cliticos-se"
      }
    },
    {
      "id": "d1-cliticos-se-ex5",
      "lessonId": "a25-clitics-se",
      "type": "cloze",
      "promptMd": "D1 Drill — ___ comas todo el pastel. (te + lo + comer)",
      "answer": "No te lo comas",
      "accepted": [
        "re:^No te lo comas$"
      ],
      "feedback": {
        "correct": "Correcto: en negativo el pronombre va antes del verbo conjugado.",
        "wrong": "En imperativos negativos coloca los clíticos antes: **No te lo comas**."
      },
      "meta": {
        "difficulty": "B1",
        "skills": [
          "write"
        ],
        "topic": "d1:cliticos-se"
      }
    },
    {
      "id": "d1-por-para-ex1",
      "lessonId": "a32-por-para-advanced",
      "type": "mcq",
      "promptMd": "D1 Drill — Gracias ___ tu apoyo constante.",
      "options": [
        "por",
        "para",
        "a"
      ],
      "answer": "por",
      "feedback": {
        "correct": "Correcto: expresa causa o agradecimiento → por.",
        "wrong": "El agradecimiento se introduce con **por**."
      },
      "meta": {
        "difficulty": "A2",
        "skills": [
          "read"
        ],
        "topic": "d1:por-para"
      }
    },
    {
      "id": "d1-por-para-ex2",
      "lessonId": "a32-por-para-advanced",
      "type": "cloze",
      "promptMd": "D1 Drill — Salgo ___ Madrid mañana por la tarde.",
      "answer": "para",
      "accepted": [
        "re:^para$"
      ],
      "feedback": {
        "correct": "Correcto: destino final → para.",
        "wrong": "Para señalar destino o meta usa **para**."
      },
      "meta": {
        "difficulty": "A2",
        "skills": [
          "write"
        ],
        "topic": "d1:por-para"
      }
    },
    {
      "id": "d1-por-para-ex3",
      "lessonId": "a32-por-para-advanced",
      "type": "mcq",
      "promptMd": "D1 Drill — Lo hago ___ ti (motivo).",
      "options": [
        "por",
        "para",
        "sobre"
      ],
      "answer": "por",
      "feedback": {
        "correct": "Correcto: motivo/causa → por.",
        "wrong": "Cuando se indica causa o motivación, elige **por**."
      },
      "meta": {
        "difficulty": "A2",
        "skills": [
          "read"
        ],
        "topic": "d1:por-para"
      }
    },
    {
      "id": "d1-por-para-ex4",
      "lessonId": "a32-por-para-advanced",
      "type": "cloze",
      "promptMd": "D1 Drill — Este regalo es ___ tu hermana.",
      "answer": "para",
      "accepted": [
        "re:^para$"
      ],
      "feedback": {
        "correct": "Correcto: destinatario → para.",
        "wrong": "Para señalar beneficiario usa **para**."
      },
      "meta": {
        "difficulty": "A2",
        "skills": [
          "write"
        ],
        "topic": "d1:por-para"
      }
    },
    {
      "id": "d1-por-para-ex5",
      "lessonId": "a32-por-para-advanced",
      "type": "mcq",
      "promptMd": "D1 Drill — Llevamos aquí dos horas ___ el tráfico.",
      "options": [
        "por",
        "para",
        "hasta"
      ],
      "answer": "por",
      "feedback": {
        "correct": "Correcto: causa que prolonga la espera → por.",
        "wrong": "Cuando la causa explica una duración, usa **por**."
      },
      "meta": {
        "difficulty": "B1",
        "skills": [
          "read"
        ],
        "topic": "d1:por-para"
      }
    },
    {
      "id": "d1-francophone-ex1",
      "lessonId": "a37-error-bank",
      "type": "cloze",
      "promptMd": "D1 Drill — Corrige el calco: *asistir la conferencia* → ___",
      "answer": "asistir a la conferencia",
      "accepted": [
        "re:^asistir a la conferencia$"
      ],
      "feedback": {
        "correct": "Correcto: *asistir* exige la preposición **a**.",
        "wrong": "Recuerda: se dice **asistir a la conferencia**, no *asistir la*."
      },
      "meta": {
        "difficulty": "B1",
        "skills": [
          "write"
        ],
        "topic": "d1:francophone-errors"
      }
    },
    {
      "id": "d1-francophone-ex2",
      "lessonId": "a37-error-bank",
      "type": "mcq",
      "promptMd": "D1 Drill — Elige la opción idiomática:",
      "options": [
        "Tomé una decisión",
        "Realicé una decisión",
        "Hice una decisión"
      ],
      "answer": "Tomé una decisión",
      "feedback": {
        "correct": "Correcto: el verbo natural es *tomar* una decisión.",
        "wrong": "Evita calcos del francés *prendre une décision*: usa **Tomé una decisión**."
      },
      "meta": {
        "difficulty": "A2",
        "skills": [
          "read"
        ],
        "topic": "d1:francophone-errors"
      }
    },
    {
      "id": "d1-francophone-ex3",
      "lessonId": "a37-error-bank",
      "type": "cloze",
      "promptMd": "D1 Drill — Estoy interesado ___ la música barroca.",
      "answer": "en",
      "accepted": [
        "re:^en$"
      ],
      "feedback": {
        "correct": "Correcto: \"interesado\" rige **en**.",
        "wrong": "Se dice **interesado en**, no *interesado por* en este contexto personal."
      },
      "meta": {
        "difficulty": "A2",
        "skills": [
          "write"
        ],
        "topic": "d1:francophone-errors"
      }
    },
    {
      "id": "d1-francophone-ex4",
      "lessonId": "a37-error-bank",
      "type": "mcq",
      "promptMd": "D1 Drill — ¿Cómo traduces 'actually' sin caer en el falso amigo?",
      "options": [
        "actualmente",
        "en realidad",
        "ahora mismo"
      ],
      "answer": "en realidad",
      "feedback": {
        "correct": "Correcto: *actually* se traduce como **en realidad** o **de hecho**.",
        "wrong": "No confundas *actually* con *actualmente* (que significa \"at present\")."
      },
      "meta": {
        "difficulty": "B1",
        "skills": [
          "read"
        ],
        "topic": "d1:francophone-errors"
      }
    },
    {
      "id": "d1-francophone-ex5",
      "lessonId": "a37-error-bank",
      "type": "cloze",
      "promptMd": "D1 Drill — Me di cuenta ___ había olvidado el dossier.",
      "answer": "de que",
      "accepted": [
        "re:^de que$"
      ],
      "feedback": {
        "correct": "Correcto: *darse cuenta* exige \"de que\".",
        "wrong": "Evita el queísmo: di **me di cuenta de que**."
      },
      "meta": {
        "difficulty": "B1",
        "skills": [
          "write"
        ],
        "topic": "d1:francophone-errors"
      }
    }
  ],
  "flashcards": [
    {
      "id": "d1-fc-001",
      "front": "Marcador 'esta semana'",
      "back": "Usa pretérito perfecto: he/has/ha + participio",
      "tag": "d1>perfecto-vs-indefinido",
      "deck": "grammar"
    },
    {
      "id": "d1-fc-002",
      "front": "Marcador 'ayer'",
      "back": "Usa pretérito indefinido (terminé, llegamos)",
      "tag": "d1>perfecto-vs-indefinido",
      "deck": "grammar"
    },
    {
      "id": "d1-fc-003",
      "front": "Mientras + verbo",
      "back": "Imperfecto para acción en curso (mientras estudiaba)",
      "tag": "d1>imperfecto-vs-indefinido",
      "deck": "grammar"
    },
    {
      "id": "d1-fc-004",
      "front": "De repente + verbo",
      "back": "Indefinido para evento puntual (de repente sonó)",
      "tag": "d1>imperfecto-vs-indefinido",
      "deck": "grammar"
    },
    {
      "id": "d1-fc-005",
      "front": "No creo que...",
      "back": "Activa subjuntivo (no creo que sea)",
      "tag": "d1>indicativo-vs-subjuntivo",
      "deck": "grammar"
    },
    {
      "id": "d1-fc-006",
      "front": "Es evidente que...",
      "back": "Mantén indicativo (es evidente que tiene)",
      "tag": "d1>indicativo-vs-subjuntivo",
      "deck": "grammar"
    },
    {
      "id": "d1-fc-007",
      "front": "Imperativo afirmativo + pronombres",
      "back": "Pega clíticos al final y añade tilde (dámelo)",
      "tag": "d1>cliticos-se",
      "deck": "grammar"
    },
    {
      "id": "d1-fc-008",
      "front": "Imperativo negativo + pronombres",
      "back": "Pronombres antes del verbo (no te lo lleves)",
      "tag": "d1>cliticos-se",
      "deck": "grammar"
    },
    {
      "id": "d1-fc-009",
      "front": "Por = causa / intercambio",
      "back": "Gracias por..., pagar por, esperar por (Am. Lat.)",
      "tag": "d1>por-para",
      "deck": "grammar"
    },
    {
      "id": "d1-fc-010",
      "front": "Para = meta / destinatario",
      "back": "Salgo para Madrid, regalo para Ana",
      "tag": "d1>por-para",
      "deck": "grammar"
    },
    {
      "id": "d1-fc-011",
      "front": "Actually ≠ actualmente",
      "back": "Traduce 'actually' como 'en realidad' o 'de hecho'",
      "tag": "d1>francophone-errors",
      "deck": "grammar"
    },
    {
      "id": "d1-fc-012",
      "front": "Asistir a",
      "back": "El verbo necesita preposición: asistir **a** la reunión",
      "tag": "d1>francophone-errors",
      "deck": "grammar"
    }
  ]
}
